{
  "${modID}:DeceptionPower": {
    "NAME": "Deception",
    "DESCRIPTIONS": [
      "When receiving unblocked attack damage, apply #b%d #yWeak back."
    ]
  },
  "${modID}:DoomPower": {
    "NAME": "Doom",
    "DESCRIPTIONS": [
      "At the end of this creature's turn, if its health is not more than #b%d, it dies."
    ]
  },
  "${modID}:FrozenEyePower": {
    "NAME": "Foresee",
    "DESCRIPTIONS": [
      "When viewing your draw pile, the cards are shown in order."
    ]
  },
  "${modID}:LetterOpenerPower": {
    "NAME": "Sharpened",
    "DESCRIPTIONS": [
      "Whenever you play a Skill this turn, deal #b%d damage to ALL enemies."
    ]
  },
  "${modID}:LoseFocusPower": {
    "NAME": "Focus Down",
    "DESCRIPTIONS": [
      "At the end of this turn, lose #b%d #yFocus."
    ]
  },
  "${modID}:NeurosurgePower": {
    "NAME": "Neurosurge",
    "DESCRIPTIONS": [
      "At the start of this creature's turn, it gains #b%d #yDoom."
    ]
  },
  "${modID}:NoDamagePower": {
    "NAME": "No Damage",
    "DESCRIPTIONS": [
      "You cannot deal attack damage."
    ]
  },
  "${modID}:RetributionPower": {
    "NAME": "Retribution",
    "DESCRIPTIONS": [
      "When attacked, your next attack deals #b%d additional damage."
    ]
  },
  "${modID}:StunPlayerPower": {
    "NAME": "Stunned",
    "DESCRIPTIONS": [
      "You cannot play cards.",
      "I cannot play cards."
    ]
  },
  "${modID}:TempStaticDischargePower": {
    "NAME": "Static",
    "DESCRIPTIONS": [
      "When receiving unblocked attack damage, #yChannel #b%d #yLightning."
    ]
  },
  "${modID}:TungstenRodPower": {
    "NAME": "Reduce Damage",
    "DESCRIPTIONS": [
      "Whenever you would lose HP this turn, lose #b%d less."
    ]
  },
  "${modID}:UntappedPower": {
    "NAME": "Untapped",
    "DESCRIPTIONS": [
      "For each unused Energy this turn, draw #b1 additional card next turn."
    ]
  },
  "${modID}:VelvetChokerPower": {
    "NAME": "Choked",
    "DESCRIPTIONS": [
      "You cannot play more than #b6 cards this turn. You have played #b%d.",
      "I can only play up to NL #r6 cards this turn."
    ]
  }
}